dualcodec/__init__.py
dualcodec/app.py
dualcodec/conf/dualcodec_ft_12hzv1.yaml
dualcodec/conf/dualcodec_ft_25hzv1.yaml
dualcodec/conf/dualcodec_train.yaml
dualcodec/conf/data/emilia_hf_raw_audio_static_batch.yaml
dualcodec/conf/machine/devbox.yaml
dualcodec/conf/model/dualcodec_12hz_16384_4096_8vq.yaml
dualcodec/conf/model/dualcodec_25hz_16384_1024_12vq.yaml
dualcodec/conf/trainer/codec_model_trainer.yaml
dualcodec/conf_tts/model/flattened_ar/llama_1x32768.yaml
dualcodec/conf_tts/model/valle_ar/llama_250M.yaml
dualcodec/conf_tts/model/valle_nar/valle_nar.yaml
dualcodec/dataset/dataset.py
dualcodec/dataset/emilia_hf.py
dualcodec/dataset/file_utils.py
dualcodec/dataset/processor.py
dualcodec/infer/dualcodec/get_model.py
dualcodec/infer/dualcodec/inference_with_semantic.py
dualcodec/infer/flattened_ar/flatten_patterns.py
dualcodec/infer/flattened_ar/inference_flattened.py
dualcodec/infer/flattened_ar/llama_wrapper.py
dualcodec/infer/flattened_ar/trainer.py
dualcodec/infer/flattened_ar/utils_flattened_ar_infer.py
dualcodec/infer/valle/api.py
dualcodec/infer/valle/cli_valle_infer.py
dualcodec/infer/valle/f5tts_gradio.py
dualcodec/infer/valle/gradio_valle_demo.py
dualcodec/infer/valle/utils_valle_infer.py
dualcodec/infer/voicebox/cli_voicebox_infer.py
dualcodec/infer/voicebox/utils_voicebox_infer.py
dualcodec/model_codec/__init__.py
dualcodec/model_codec/cnn.py
dualcodec/model_codec/dac_layers.py
dualcodec/model_codec/dac_model.py
dualcodec/model_codec/dac_quantize.py
dualcodec/model_codec/discriminator.py
dualcodec/model_codec/dualcodec_model.py
dualcodec/model_codec/loss.py
dualcodec/model_codec/trainer.py
dualcodec/model_tts/valle_ar/llama_wrapper.py
dualcodec/model_tts/valle_nar/modeling_llama.py
dualcodec/model_tts/valle_nar/valle_nar_model.py
dualcodec/model_tts/voicebox/llama_nar.py
dualcodec/model_tts/voicebox/modeling_llama.py
dualcodec/model_tts/voicebox/vocoder_model.py
dualcodec/model_tts/voicebox/voicebox_models.py
dualcodec/utils/__init__.py
dualcodec-0.4.2.dist-info/METADATA
dualcodec-0.4.2.dist-info/WHEEL
dualcodec-0.4.2.dist-info/licenses/LICENSE
dualcodec-0.4.2.dist-info/RECORD
