Metadata-Version: 2.4
Name: dualcodec
Version: 0.4.2
Summary: The DualCodec neural audio codec.
License: MIT
License-File: LICENSE
Requires-Python: >=3.9
Requires-Dist: cached-path
Requires-Dist: descript-audiotools>=0.7.2
Requires-Dist: easydict
Requires-Dist: einops
Requires-Dist: huggingface-hub[cli]
Requires-Dist: hydra-core
Requires-Dist: safetensors
Requires-Dist: torch
Requires-Dist: torchaudio
Requires-Dist: transformers>=4.30.0
Provides-Extra: tts
Requires-Dist: accelerate>=1.0; extra == 'tts'
Requires-Dist: cn2an; extra == 'tts'
Requires-Dist: datasets; extra == 'tts'
Requires-Dist: f5-tts; extra == 'tts'
Requires-Dist: openai-whisper; extra == 'tts'
